odoo/addons/product_category_active/README.rst
odoo/addons/product_category_active/__init__.py
odoo/addons/product_category_active/__manifest__.py
odoo/addons/product_category_active/i18n/es.po
odoo/addons/product_category_active/i18n/product_category_active.pot
odoo/addons/product_category_active/i18n/product_category_archive.pot
odoo/addons/product_category_active/models/__init__.py
odoo/addons/product_category_active/models/product.py
odoo/addons/product_category_active/readme/CONTRIBUTORS.rst
odoo/addons/product_category_active/readme/DESCRIPTION.rst
odoo/addons/product_category_active/readme/ROADMAP.rst
odoo/addons/product_category_active/readme/USAGE.rst
odoo/addons/product_category_active/static/description/icon.png
odoo/addons/product_category_active/static/description/index.html
odoo/addons/product_category_active/tests/__init__.py
odoo/addons/product_category_active/tests/test_product_category_archive.py
odoo/addons/product_category_active/views/product_views.xml
odoo12_addon_product_category_active-12.0.1.0.1.dist-info/METADATA
odoo12_addon_product_category_active-12.0.1.0.1.dist-info/WHEEL
odoo12_addon_product_category_active-12.0.1.0.1.dist-info/top_level.txt
odoo12_addon_product_category_active-12.0.1.0.1.dist-info/RECORD
